setup.cfg
setup.py
fjlc/__init__.py
fjlc/lexical_classifier.py
fjlc/main.py
fjlc.egg-info/PKG-INFO
fjlc.egg-info/SOURCES.txt
fjlc.egg-info/dependency_links.txt
fjlc.egg-info/entry_points.txt
fjlc.egg-info/requires.txt
fjlc.egg-info/top_level.txt
fjlc/classifier/__init__.py
fjlc/classifier/classifier.py
fjlc/classifier/classifier_options.py
fjlc/classifier/sentence/__init__.py
fjlc/classifier/sentence/lexical_parser.py
fjlc/classifier/sentence/lexical_token.py
fjlc/lexicon/__init__.py
fjlc/lexicon/lexicon_creator.py
fjlc/lexicon/container/__init__.py
fjlc/lexicon/container/adjectives.py
fjlc/lexicon/container/prior_polarity_lexicon.py
fjlc/lexicon/container/token_trie.py
fjlc/preprocessing/__init__.py
fjlc/preprocessing/filters/__init__.py
fjlc/preprocessing/filters/canonical_form.py
fjlc/preprocessing/filters/filters.py
fjlc/preprocessing/filters/regex_filters.py
fjlc/preprocessing/preprocessors/__init__.py
fjlc/preprocessing/preprocessors/tweet_n_grams_pmi.py
fjlc/res/data/canonical.json
fjlc/res/data/lexicon.pmi.json
fjlc/res/data/options.pmi.json
fjlc/utils/__init__.py
fjlc/utils/file_utils.py
fjlc/utils/json_utils.py
fjlc/utils/map_utils.py
fjlc/utils/reader/__init__.py
fjlc/utils/reader/data_set_reader.py
fjlc/utils/reader/line_reader.py