Metadata-Version: 1.1
Name: fjlc
Version: 1.0.3
Summary: A Python port of the Fredriksen-Jahren Lexicon Classifier
Home-page: https://github.com/draperunner/fjlc
Author: Valerij Fredriksen and Brage Ekroll Jahren and Mats Byrkjeland
Author-email: matsbyr@gmail.com
License: MIT
Keywords: twitter sentiment analysis lexicon
Platform: UNKNOWN
Classifier: Development Status :: 4 - Beta
Classifier: Intended Audience :: Developers
Classifier: Topic :: Scientific/Engineering :: Artificial Intelligence
Classifier: License :: OSI Approved :: MIT License
Classifier: Programming Language :: Python :: 3
Classifier: Programming Language :: Python :: 3.3
Classifier: Programming Language :: Python :: 3.4
Classifier: Programming Language :: Python :: 3.5
